py_static_dtm/__init__.py
py_static_dtm/kml_utils.py
py_static_dtm/polygon_utils.py
py_static_dtm/py.typed
py_static_dtm/static_dtm.py
py_static_dtm-1.0.1.dist-info/LICENSE
py_static_dtm-1.0.1.dist-info/METADATA
py_static_dtm-1.0.1.dist-info/WHEEL
py_static_dtm-1.0.1.dist-info/top_level.txt
py_static_dtm-1.0.1.dist-info/RECORD
