Metadata-Version: 2.1
Name: py-static-dtm
Version: 1.0.1
Summary: A custom DTM object that returns a constant value in a certain polygon
Author-email: Ben Sembira <classified@classified.classified>
Project-URL: Homepage, https://github.com/ben-sembira-1/py-static-dtm
Project-URL: Issues, https://github.com/ben-sembira-1/py-static-dtm/issues
Classifier: Programming Language :: Python :: 3
Classifier: License :: OSI Approved :: MIT License
Classifier: Operating System :: OS Independent
Requires-Python: >=3.8
License-File: LICENSE
Requires-Dist: fastkml
Requires-Dist: lxml
Requires-Dist: shapely
Requires-Dist: pyproj
Requires-Dist: numpy
Requires-Dist: pytest
